{
  "1": {
    "id": 1,
    "itemType": "Armor",
    "itemName": "기본 갑옷",
    "itemDescription": "나쁘지 않음",
    "itemIndex": 0,
    "hp": 0.0,
    "hpIncreaseRate": 0.0,
    "hpRecovery": 0.0,
    "stamina": 0.0,
    "staminaRecovery": 0.0,
    "attackDamage": 0.0,
    "attackSpeed": 0.0,
    "attackCooldown": 0.0,
    "armor": 0.0,
    "magicResistance": 0.0,
    "moveSpeed": 0.0,
    "dashCooldown": 0.0,
    "dashStamina": 0.0
  },
  "2": {
    "id": 2,
    "itemType": "Bottom",
    "itemName": "기본 하의",
    "itemDescription": "나이롱 좋아",
    "itemIndex": 0,
    "hp": 0.0,
    "hpIncreaseRate": 0.0,
    "hpRecovery": 0.0,
    "stamina": 0.0,
    "staminaRecovery": 0.0,
    "attackDamage": 0.0,
    "attackSpeed": 0.0,
    "attackCooldown": 0.0,
    "armor": 0.0,
    "magicResistance": 0.0,
    "moveSpeed": 0.0,
    "dashCooldown": 0.0,
    "dashStamina": 0.0
  },
  "3": {
    "id": 3,
    "itemType": "Helmet",
    "itemName": "기본 헬멧",
    "itemDescription": "걍 대충해",
    "itemIndex": 0,
    "hp": 0.0,
    "hpIncreaseRate": 0.0,
    "hpRecovery": 0.0,
    "stamina": 0.0,
    "staminaRecovery": 0.0,
    "attackDamage": 0.0,
    "attackSpeed": 0.0,
    "attackCooldown": 0.0,
    "armor": 0.0,
    "magicResistance": 0.0,
    "moveSpeed": 0.0,
    "dashCooldown": 0.0,
    "dashStamina": 0.0
  },
  "4": {
    "id": 4,
    "itemType": "Gloves",
    "itemName": "기본 장갑",
    "itemDescription": "괜찮은듯?",
    "itemIndex": 0,
    "hp": 0.0,
    "hpIncreaseRate": 0.0,
    "hpRecovery": 0.0,
    "stamina": 0.0,
    "staminaRecovery": 0.0,
    "attackDamage": 0.0,
    "attackSpeed": 0.0,
    "attackCooldown": 0.0,
    "armor": 0.0,
    "magicResistance": 0.0,
    "moveSpeed": 0.0,
    "dashCooldown": 0.0,
    "dashStamina": 0.0
  },
  "5": {
    "id": 5,
    "itemType": "Boot",
    "itemName": "기본 신발",
    "itemDescription": "한땀한땀 수제작",
    "itemIndex": 0,
    "hp": 0.0,
    "hpIncreaseRate": 0.0,
    "hpRecovery": 0.0,
    "stamina": 0.0,
    "staminaRecovery": 0.0,
    "attackDamage": 0.0,
    "attackSpeed": 0.0,
    "attackCooldown": 0.0,
    "armor": 0.0,
    "magicResistance": 0.0,
    "moveSpeed": 0.0,
    "dashCooldown": 0.0,
    "dashStamina": 0.0
  }
}